{
  "project_info": {
    "project_number": "192120269290",
    "project_id": "push-notification-8d3b0",
    "storage_bucket": "push-notification-8d3b0.appspot.com"
  },
  "client": [
    {
      "client_info": {
        "mobilesdk_app_id": "1:192120269290:android:564870c267480f909aea93",
        "android_client_info": {
          "package_name": "com.example.pushnotificationapp"
        }
      },
      "oauth_client": [
        {
          "client_id": "192120269290-q2m37gs6vk0ol60umphqc6b2i4e45m3d.apps.googleusercontent.com",
          "client_type": 3
        }
      ],
      "api_key": [
        {
          "current_key": "AIzaSyCVQDn1kKxqdDPZFXX4CCIlckTtHfSMtls"
        }
      ],
      "services": {
        "appinvite_service": {
          "other_platform_oauth_client": [
            {
              "client_id": "192120269290-q2m37gs6vk0ol60umphqc6b2i4e45m3d.apps.googleusercontent.com",
              "client_type": 3
            }
          ]
        }
      }
    }
  ],
  "configuration_version": "1"
}